MANIFEST.in
README.txt
setup.py
app_monitor.egg-info/PKG-INFO
app_monitor.egg-info/SOURCES.txt
app_monitor.egg-info/dependency_links.txt
app_monitor.egg-info/requires.txt
app_monitor.egg-info/top_level.txt
monitor/__init__.py
monitor/config.py
monitor/inner_db
monitor/notifier.py
monitor/run-check.py
monitor/scheduler.py
monitor/tests.py