Metadata-Version: 1.0
Name: app-monitor
Version: 0.1.3
Summary: Check script scheduler
Home-page: UNKNOWN
Author: Anthony Tresontani
Author-email: dev.tresontani@gmail.com
License: UNKNOWN
Platform: UNKNOWN
